Metadata-Version: 1.0
Name: annotationjf
Version: 0.0.5
Summary: annotation
Home-page: https://github.com/ss-lab-cancerunit/cobra
Author: jun
Author-email: jh2259@cam.ac.uk
License: UNKNOWN
Platform: UNKNOWN
